{
    "album": "The Dialogue Journal",
    "episodes": [
        {
            "album": "The Dialogue Journal",
            "artist": "The Dialogue Journal",
            "date_added": "2021-09-13T19:14:53",
            "genre": "Podcast",
            "location": "https://media.blubrry.com/dialogue_journal/www.dialoguejournal.com/wp-content/uploads/podcasts/dialogueoutloud5.mp3",
            "name": "Dialogue Out Loud #5: Ace of Saints",
            "persistent_id": "F83655A29F8B000E",
            "podcast": true,
            "release_date": "2020-11-27T21:43:41",
            "size": 51325304,
            "sort_album": "Dialogue Journal",
            "sort_artist": "Dialogue Journal",
            "total_time": 2566000,
            "track_id": 9666,
            "track_type": "URL",
            "unplayed": true
        },
        {
            "album": "The Dialogue Journal",
            "artist": "The Dialogue Journal",
            "date_added": "2021-09-13T19:14:53",
            "genre": "Podcast",
            "location": "https://media.blubrry.com/dialogue_journal/www.dialoguejournal.com/wp-content/uploads/podcasts/dialogueoutloud6.mp3",
            "name": "Dialogue Out Loud #6: Mormon Saga by Maurine Whipple",
            "persistent_id": "C2044D21D6007920",
            "podcast": true,
            "release_date": "2020-12-04T16:10:04",
            "size": 67575557,
            "sort_album": "Dialogue Journal",
            "sort_artist": "Dialogue Journal",
            "total_time": 3379000,
            "track_id": 9668,
            "track_type": "URL",
            "unplayed": true
        },
        {
            "album": "The Dialogue Journal",
            "artist": "The Dialogue Journal",
            "date_added": "2021-09-13T19:14:53",
            "genre": "Podcast",
            "location": "https://media.blubrry.com/dialogue_journal/www.dialoguejournal.com/wp-content/uploads/podcasts/dialoguepodcast_85.mp3",
            "name": "Dialogue Sunday Study #33 w/Aimee Evans Hickman",
            "persistent_id": "6D49B1C3C4D03128",
            "podcast": true,
            "release_date": "2020-12-06T23:46:40",
            "size": 66847486,
            "sort_album": "Dialogue Journal",
            "sort_artist": "Dialogue Journal",
            "total_time": 2785000,
            "track_id": 9670,
            "track_type": "URL",
            "unplayed": true
        },
        {
            "album": "The Dialogue Journal",
            "artist": "The Dialogue Journal",
            "date_added": "2021-09-13T19:14:53",
            "genre": "Podcast",
            "location": "https://media.blubrry.com/dialogue_journal/www.dialoguejournal.com/wp-content/uploads/podcasts/dialogueoutloud7.mp3",
            "name": "Dialogue Out Loud #7: Who Brought Forth This Christmas Demon by Larry Menlove",
            "persistent_id": "04BD6EE187C02BBD",
            "podcast": true,
            "release_date": "2020-12-11T19:05:03",
            "size": 42845434,
            "sort_album": "Dialogue Journal",
            "sort_artist": "Dialogue Journal",
            "total_time": 2142000,
            "track_id": 9672,
            "track_type": "URL",
            "unplayed": true
        },
        {
            "album": "The Dialogue Journal",
            "artist": "The Dialogue Journal",
            "date_added": "2021-09-13T19:14:53",
            "genre": "Podcast",
            "location": "https://media.blubrry.com/dialogue_journal/www.dialoguejournal.com/wp-content/uploads/podcasts/dialoguepodcast_86.mp3",
            "name": "Dialogue Sunday Study #34 w/Joseph Spencer",
            "persistent_id": "85BC8527EEF2F861",
            "podcast": true,
            "release_date": "2020-12-14T01:59:57",
            "size": 124340279,
            "sort_album": "Dialogue Journal",
            "sort_artist": "Dialogue Journal",
            "total_time": 5181000,
            "track_id": 9674,
            "track_type": "URL",
            "unplayed": true
        },
        {
            "album": "The Dialogue Journal",
            "artist": "The Dialogue Journal",
            "date_added": "2021-09-13T19:14:53",
            "genre": "Podcast",
            "location": "https://media.blubrry.com/dialogue_journal/www.dialoguejournal.com/wp-content/uploads/podcasts/dialoguepodcast_87.mp3",
            "name": "Dialogue Fireside #3 w/Brian Kershisnik",
            "persistent_id": "7B9080E8926DE420",
            "podcast": true,
            "release_date": "2020-12-21T21:31:51",
            "size": 105903264,
            "sort_album": "Dialogue Journal",
            "sort_artist": "Dialogue Journal",
            "total_time": 4413000,
            "track_id": 9676,
            "track_type": "URL",
            "unplayed": true
        },
        {
            "album": "The Dialogue Journal",
            "artist": "The Dialogue Journal",
            "date_added": "2021-09-13T19:14:53",
            "genre": "Podcast",
            "location": "https://media.blubrry.com/dialogue_journal/www.dialoguejournal.com/wp-content/uploads/podcasts/dialoguebookreport_8.mp3",
            "name": "Dialogue Book Report #8: Andrew and Andrew on 2020 LDS books",
            "persistent_id": "48D6CBE8A9D48661",
            "podcast": true,
            "release_date": "2021-01-05T00:04:36",
            "size": 52765173,
            "sort_album": "Dialogue Journal",
            "sort_artist": "Dialogue Journal",
            "total_time": 2638000,
            "track_id": 9678,
            "track_type": "URL",
            "unplayed": true
        },
        {
            "album": "The Dialogue Journal",
            "artist": "The Dialogue Journal",
            "date_added": "2021-09-13T19:14:53",
            "genre": "Podcast",
            "location": "https://media.blubrry.com/dialogue_journal/www.dialoguejournal.com/wp-content/uploads/podcasts/dialoguepodcast_88.mp3",
            "name": "Dialogue Fireside #4 w/Benjamin Park",
            "persistent_id": "388A258F75450AF1",
            "podcast": true,
            "release_date": "2021-01-20T00:36:25",
            "size": 120057660,
            "sort_album": "Dialogue Journal",
            "sort_artist": "Dialogue Journal",
            "total_time": 5002000,
            "track_id": 9680,
            "track_type": "URL",
            "unplayed": true
        },
        {
            "album": "The Dialogue Journal",
            "artist": "The Dialogue Journal",
            "date_added": "2021-09-13T19:14:53",
            "genre": "Podcast",
            "location": "https://media.blubrry.com/dialogue_journal/www.dialoguejournal.com/wp-content/uploads/podcasts/dialoguepodcast_89.mp3",
            "name": "Dialogue Sunday Study #35 w/Kif Augustine",
            "persistent_id": "447BFF6AB4866613",
            "podcast": true,
            "release_date": "2021-01-25T17:27:50",
            "size": 98963051,
            "sort_album": "Dialogue Journal",
            "sort_artist": "Dialogue Journal",
            "total_time": 4123000,
            "track_id": 9682,
            "track_type": "URL",
            "unplayed": true
        },
        {
            "album": "The Dialogue Journal",
            "artist": "The Dialogue Journal",
            "date_added": "2021-09-13T19:14:53",
            "genre": "Podcast",
            "location": "https://media.blubrry.com/dialogue_journal/www.dialoguejournal.com/wp-content/uploads/podcasts/dialoguebookreport_9.mp3",
            "name": "Dialogue Book Report #9: Novels of polygamy and the Great Basin frontier",
            "persistent_id": "E41A7FA41077ED25",
            "play_count": 1,
            "play_date": 3702012709,
            "play_date_utc": "2021-04-23T14:51:49",
            "podcast": true,
            "release_date": "2021-01-29T16:51:33",
            "size": 57395638,
            "sort_album": "Dialogue Journal",
            "sort_artist": "Dialogue Journal",
            "total_time": 2870000,
            "track_id": 9684,
            "track_type": "URL"
        },
        {
            "album": "The Dialogue Journal",
            "artist": "The Dialogue Journal",
            "date_added": "2021-09-13T19:14:53",
            "genre": "Podcast",
            "location": "https://media.blubrry.com/dialogue_journal/www.dialoguejournal.com/wp-content/uploads/podcasts/dialoguepodcast_topics1.mp3",
            "name": "Dialogue Topic Pages #1: First Vision",
            "persistent_id": "D794BBF9B1C6401A",
            "podcast": true,
            "release_date": "2021-02-04T02:23:53",
            "size": 26385157,
            "sort_album": "Dialogue Journal",
            "sort_artist": "Dialogue Journal",
            "total_time": 1319000,
            "track_id": 9686,
            "track_type": "URL",
            "unplayed": true
        },
        {
            "album": "The Dialogue Journal",
            "artist": "The Dialogue Journal",
            "date_added": "2021-09-13T19:14:53",
            "genre": "Podcast",
            "location": "https://media.blubrry.com/dialogue_journal/www.dialoguejournal.com/wp-content/uploads/podcasts/dialoguepodcast_90.mp3",
            "name": "Dialogue Sunday Study #36 w/Elray Henriksen",
            "persistent_id": "4C65765117FEE933",
            "podcast": true,
            "release_date": "2021-02-14T23:45:03",
            "size": 102649210,
            "sort_album": "Dialogue Journal",
            "sort_artist": "Dialogue Journal",
            "total_time": 4277000,
            "track_id": 9688,
            "track_type": "URL",
            "unplayed": true
        },
        {
            "album": "The Dialogue Journal",
            "artist": "The Dialogue Journal",
            "date_added": "2021-09-13T19:14:53",
            "genre": "Podcast",
            "location": "https://media.blubrry.com/dialogue_journal/www.dialoguejournal.com/wp-content/uploads/podcasts/dialoguepodcast_91.mp3",
            "name": "Dialogue Fireside #5 w/Jill Mulvay Derr",
            "persistent_id": "B4FD77C3D6A19E3B",
            "play_count": 1,
            "play_date": 3703746226,
            "play_date_utc": "2021-05-13T16:23:46",
            "podcast": true,
            "release_date": "2021-02-24T04:11:13",
            "size": 113505523,
            "sort_album": "Dialogue Journal",
            "sort_artist": "Dialogue Journal",
            "total_time": 4729000,
            "track_id": 9690,
            "track_type": "URL"
        },
        {
            "album": "The Dialogue Journal",
            "artist": "The Dialogue Journal",
            "date_added": "2021-09-13T19:14:53",
            "genre": "Podcast",
            "location": "https://media.blubrry.com/dialogue_journal/www.dialoguejournal.com/wp-content/uploads/podcasts/dialoguetopics_1.mp3",
            "name": "Dialogue Topic Pages Podcast #2: Race",
            "persistent_id": "5B4A1AAB6F587030",
            "podcast": true,
            "release_date": "2021-02-27T01:11:30",
            "size": 58325597,
            "sort_album": "Dialogue Journal",
            "sort_artist": "Dialogue Journal",
            "total_time": 2916000,
            "track_id": 9692,
            "track_type": "URL",
            "unplayed": true
        },
        {
            "album": "The Dialogue Journal",
            "artist": "The Dialogue Journal",
            "date_added": "2021-09-13T19:14:53",
            "genre": "Podcast",
            "location": "https://media.blubrry.com/dialogue_journal/www.dialoguejournal.com/wp-content/uploads/podcasts/dialoguepodcast_92.mp3",
            "name": "Dialogue Sunday Study #37 w/Cathy Stokes",
            "persistent_id": "752EBCBE7F23AC03",
            "podcast": true,
            "release_date": "2021-03-01T16:38:17",
            "size": 85751924,
            "sort_album": "Dialogue Journal",
            "sort_artist": "Dialogue Journal",
            "total_time": 3573000,
            "track_id": 9694,
            "track_type": "URL",
            "unplayed": true
        },
        {
            "album": "The Dialogue Journal",
            "artist": "The Dialogue Journal",
            "date_added": "2021-09-13T19:14:53",
            "genre": "Podcast",
            "location": "https://media.blubrry.com/dialogue_journal/www.dialoguejournal.com/wp-content/uploads/podcasts/dialoguepodcast_93.mp3",
            "name": "Dialogue Sunday Study #38 w/Melody Newey Johnson",
            "persistent_id": "97C585D78DB8A8C5",
            "podcast": true,
            "release_date": "2021-03-15T01:50:21",
            "size": 144685037,
            "sort_album": "Dialogue Journal",
            "sort_artist": "Dialogue Journal",
            "total_time": 4521000,
            "track_id": 9696,
            "track_type": "URL",
            "unplayed": true
        },
        {
            "album": "The Dialogue Journal",
            "artist": "The Dialogue Journal",
            "date_added": "2021-09-13T19:14:53",
            "genre": "Podcast",
            "location": "https://media.blubrry.com/dialogue_journal/www.dialoguejournal.com/wp-content/uploads/podcasts/dialoguetopics_3.mp3",
            "name": "Dialogue Topic Pages Podcast #3: Feminism",
            "persistent_id": "526A61738ED5B057",
            "podcast": true,
            "release_date": "2021-03-18T18:19:11",
            "size": 66565140,
            "sort_album": "Dialogue Journal",
            "sort_artist": "Dialogue Journal",
            "total_time": 3328000,
            "track_id": 9698,
            "track_type": "URL",
            "unplayed": true
        },
        {
            "album": "The Dialogue Journal",
            "artist": "The Dialogue Journal",
            "date_added": "2021-09-13T19:14:53",
            "genre": "Podcast",
            "location": "https://media.blubrry.com/dialogue_journal/www.dialoguejournal.com/wp-content/uploads/podcasts/dialoguepodcast_94.mp3",
            "name": "Dialogue Fireside #6 w/Terryl Givens",
            "persistent_id": "10DBD9E4DB0E5404",
            "podcast": true,
            "release_date": "2021-03-23T01:24:21",
            "size": 102649451,
            "sort_album": "Dialogue Journal",
            "sort_artist": "Dialogue Journal",
            "total_time": 4277000,
            "track_id": 9700,
            "track_type": "URL",
            "unplayed": true
        },
        {
            "album": "The Dialogue Journal",
            "artist": "The Dialogue Journal",
            "date_added": "2021-09-13T19:14:53",
            "genre": "Podcast",
            "location": "https://media.blubrry.com/dialogue_journal/www.dialoguejournal.com/wp-content/uploads/podcasts/dialoguepodcast_95.mp3",
            "name": "Dialogue Gospel Study #39 w/Darius Gray",
            "persistent_id": "80503DE5DD0F42CD",
            "podcast": true,
            "release_date": "2021-03-29T00:15:18",
            "size": 211927369,
            "sort_album": "Dialogue Journal",
            "sort_artist": "Dialogue Journal",
            "total_time": 5298000,
            "track_id": 9702,
            "track_type": "URL",
            "unplayed": true
        },
        {
            "album": "The Dialogue Journal",
            "artist": "The Dialogue Journal",
            "date_added": "2021-09-13T19:14:53",
            "genre": "Podcast",
            "location": "https://media.blubrry.com/dialogue_journal/www.dialoguejournal.com/wp-content/uploads/podcasts/dialoguepodcast_96.mp3",
            "name": "Dialogue Gospel Study #40 w/David-James Gonzales",
            "persistent_id": "DD80A0ECFB25383F",
            "play_count": 1,
            "play_date": 3701521922,
            "play_date_utc": "2021-04-17T22:32:02",
            "podcast": true,
            "release_date": "2021-04-12T02:11:35",
            "size": 150714112,
            "sort_album": "Dialogue Journal",
            "sort_artist": "Dialogue Journal",
            "total_time": 3768000,
            "track_id": 9704,
            "track_type": "URL"
        },
        {
            "album": "The Dialogue Journal",
            "artist": "The Dialogue Journal",
            "date_added": "2021-09-13T19:14:53",
            "genre": "Podcast",
            "location": "https://media.blubrry.com/dialogue_journal/www.dialoguejournal.com/wp-content/uploads/podcasts/dialoguepodcast_topics4.mp3",
            "name": "Dialogue Topic Pages #4: Temples",
            "persistent_id": "7A812FCBEC1C5D67",
            "podcast": true,
            "release_date": "2021-04-15T23:05:22",
            "size": 45415456,
            "sort_album": "Dialogue Journal",
            "sort_artist": "Dialogue Journal",
            "total_time": 2271000,
            "track_id": 9706,
            "track_type": "URL",
            "unplayed": true
        },
        {
            "album": "The Dialogue Journal",
            "artist": "The Dialogue Journal",
            "date_added": "2021-09-13T19:14:53",
            "genre": "Podcast",
            "location": "https://media.blubrry.com/dialogue_journal/www.dialoguejournal.com/wp-content/uploads/podcasts/dialoguepodcast_97.mp3",
            "name": "Dialogue Fireside #7 w/Rosemary Card",
            "persistent_id": "2DC7923CBD3C9088",
            "play_count": 1,
            "play_date": 3710577462,
            "play_date_utc": "2021-07-31T17:57:42",
            "podcast": true,
            "release_date": "2021-04-20T18:23:29",
            "size": 145006879,
            "sort_album": "Dialogue Journal",
            "sort_artist": "Dialogue Journal",
            "total_time": 3625000,
            "track_id": 9708,
            "track_type": "URL"
        },
        {
            "album": "The Dialogue Journal",
            "artist": "The Dialogue Journal",
            "date_added": "2021-09-13T19:14:53",
            "genre": "Podcast",
            "location": "https://media.blubrry.com/dialogue_journal/www.dialoguejournal.com/wp-content/uploads/podcasts/dialoguepodcast_98.mp3",
            "name": "Dialogue Gospel Study #41 w/Heather Sundahl",
            "persistent_id": "926138B91B06EDFC",
            "podcast": true,
            "release_date": "2021-04-26T02:38:39",
            "size": 162965541,
            "sort_album": "Dialogue Journal",
            "sort_artist": "Dialogue Journal",
            "total_time": 4074000,
            "track_id": 9710,
            "track_type": "URL",
            "unplayed": true
        },
        {
            "album": "The Dialogue Journal",
            "artist": "The Dialogue Journal",
            "date_added": "2021-09-13T19:14:53",
            "genre": "Podcast",
            "location": "https://media.blubrry.com/dialogue_journal/www.dialoguejournal.com/wp-content/uploads/podcasts/dialoguebookreport_10.mp3",
            "name": "Dialogue Book Report #10: The best of 2020–Creative Nonfiction and Poetry",
            "persistent_id": "26558D4DAA8CC024",
            "play_count": 1,
            "play_date": 3712748044,
            "play_date_utc": "2021-08-25T20:54:04",
            "podcast": true,
            "release_date": "2021-04-29T17:27:53",
            "size": 68085376,
            "sort_album": "Dialogue Journal",
            "sort_artist": "Dialogue Journal",
            "total_time": 3404000,
            "track_id": 9712,
            "track_type": "URL"
        },
        {
            "album": "The Dialogue Journal",
            "artist": "The Dialogue Journal",
            "date_added": "2021-09-13T19:14:53",
            "genre": "Podcast",
            "location": "https://media.blubrry.com/dialogue_journal/www.dialoguejournal.com/wp-content/uploads/podcasts/dialogueoutloud_8.mp3",
            "name": "Dialogue Out Loud #8: Confession by Sylvette Wolfe",
            "persistent_id": "4AF8E3937325FDBF",
            "play_count": 1,
            "play_date": 3712816614,
            "play_date_utc": "2021-08-26T15:56:54",
            "podcast": true,
            "release_date": "2021-05-04T00:00:26",
            "size": 25885216,
            "sort_album": "Dialogue Journal",
            "sort_artist": "Dialogue Journal",
            "total_time": 1294000,
            "track_id": 9714,
            "track_type": "URL"
        },
        {
            "album": "The Dialogue Journal",
            "artist": "The Dialogue Journal",
            "date_added": "2021-09-13T19:14:53",
            "genre": "Podcast",
            "location": "https://media.blubrry.com/dialogue_journal/www.dialoguejournal.com/wp-content/uploads/podcasts/dialoguepodcast_99.mp3",
            "name": "Dialogue Gospel Study #42 w/Sylvia Cabus",
            "persistent_id": "F95E0059F5FAFFF0",
            "podcast": true,
            "release_date": "2021-05-10T04:28:02",
            "size": 82025446,
            "sort_album": "Dialogue Journal",
            "sort_artist": "Dialogue Journal",
            "total_time": 3417000,
            "track_id": 9716,
            "track_type": "URL",
            "unplayed": true
        },
        {
            "album": "The Dialogue Journal",
            "artist": "The Dialogue Journal",
            "date_added": "2021-09-13T19:14:53",
            "genre": "Podcast",
            "location": "https://media.blubrry.com/dialogue_journal/www.dialoguejournal.com/wp-content/uploads/podcasts/dialogueoutloud_9.mp3",
            "name": "Dialogue Out Loud #9: Called Not to Serve by Neal David Silvester",
            "persistent_id": "FF03370820EF91AD",
            "play_count": 1,
            "play_date": 3713019279,
            "play_date_utc": "2021-08-29T00:14:39",
            "podcast": true,
            "release_date": "2021-05-11T22:47:53",
            "size": 28925304,
            "sort_album": "Dialogue Journal",
            "sort_artist": "Dialogue Journal",
            "total_time": 1446000,
            "track_id": 9718,
            "track_type": "URL"
        },
        {
            "album": "The Dialogue Journal",
            "artist": "The Dialogue Journal",
            "date_added": "2021-09-13T19:14:53",
            "genre": "Podcast",
            "location": "https://media.blubrry.com/dialogue_journal/www.dialoguejournal.com/wp-content/uploads/podcasts/dialoguepodcast_100.mp3",
            "name": "Dialogue Fireside #8 w/Marlena Wilding",
            "persistent_id": "799E59BB0C9CF247",
            "play_count": 1,
            "play_date": 3705761986,
            "play_date_utc": "2021-06-06T00:19:46",
            "podcast": true,
            "release_date": "2021-05-19T23:00:16",
            "size": 161519402,
            "sort_album": "Dialogue Journal",
            "sort_artist": "Dialogue Journal",
            "total_time": 4038000,
            "track_id": 9720,
            "track_type": "URL"
        },
        {
            "album": "The Dialogue Journal",
            "artist": "The Dialogue Journal",
            "date_added": "2021-09-13T19:14:53",
            "genre": "Podcast",
            "location": "https://media.blubrry.com/dialogue_journal/www.dialoguejournal.com/wp-content/uploads/podcasts/dialoguepodcast_topics5.mp3",
            "name": "Dialogue Topic Pages #5: The Book of Abraham",
            "persistent_id": "499D33DA3F04ADDC",
            "podcast": true,
            "release_date": "2021-05-21T23:56:36",
            "size": 37525216,
            "sort_album": "Dialogue Journal",
            "sort_artist": "Dialogue Journal",
            "total_time": 1876000,
            "track_id": 9722,
            "track_type": "URL",
            "unplayed": true
        },
        {
            "album": "The Dialogue Journal",
            "artist": "The Dialogue Journal",
            "date_added": "2021-09-13T19:14:53",
            "genre": "Podcast",
            "location": "https://media.blubrry.com/dialogue_journal/www.dialoguejournal.com/wp-content/uploads/podcasts/dialoguepodcast_101.mp3",
            "name": "Dialogue Gospel Study #43 with Ben Abbott",
            "persistent_id": "BF9953EE3D105E41",
            "podcast": true,
            "release_date": "2021-05-23T22:24:52",
            "size": 115188626,
            "sort_album": "Dialogue Journal",
            "sort_artist": "Dialogue Journal",
            "total_time": 4799000,
            "track_id": 9724,
            "track_type": "URL",
            "unplayed": true
        },
        {
            "album": "The Dialogue Journal",
            "artist": "The Dialogue Journal",
            "date_added": "2021-09-13T19:14:53",
            "genre": "Podcast",
            "location": "https://media.blubrry.com/dialogue_journal/www.dialoguejournal.com/wp-content/uploads/podcasts/dialogueoutloud_10.mp3",
            "name": "Dialogue Out Loud #10: Assuming Power by Linda Hoffman Kimball",
            "persistent_id": "2ED5E7D1B9897D3C",
            "podcast": true,
            "release_date": "2021-05-27T23:56:16",
            "size": 18465353,
            "sort_album": "Dialogue Journal",
            "sort_artist": "Dialogue Journal",
            "total_time": 923000,
            "track_id": 9726,
            "track_type": "URL",
            "unplayed": true
        },
        {
            "album": "The Dialogue Journal",
            "artist": "The Dialogue Journal",
            "date_added": "2021-09-13T19:14:53",
            "genre": "Podcast",
            "location": "https://media.blubrry.com/dialogue_journal/www.dialoguejournal.com/wp-content/uploads/podcasts/dialoguepodcast_102.mp3",
            "name": "Dialogue Gospel Study #44 with Rachel Mumford",
            "persistent_id": "2C2218E80A528FE8",
            "podcast": true,
            "release_date": "2021-06-13T22:38:31",
            "size": 119823167,
            "sort_album": "Dialogue Journal",
            "sort_artist": "Dialogue Journal",
            "total_time": 3744000,
            "track_id": 9728,
            "track_type": "URL",
            "unplayed": true
        },
        {
            "album": "The Dialogue Journal",
            "artist": "The Dialogue Journal",
            "date_added": "2021-09-13T19:14:53",
            "genre": "Podcast",
            "location": "https://media.blubrry.com/dialogue_journal/www.dialoguejournal.com/wp-content/uploads/podcasts/dialoguepodcasts_topics6.mp3",
            "name": "Dialogue Topic Pages #6: LGBT Issues",
            "persistent_id": "BBAA2C84F83A8EFF",
            "podcast": true,
            "release_date": "2021-06-18T19:53:10",
            "size": 59655136,
            "sort_album": "Dialogue Journal",
            "sort_artist": "Dialogue Journal",
            "total_time": 2983000,
            "track_id": 9730,
            "track_type": "URL",
            "unplayed": true
        },
        {
            "album": "The Dialogue Journal",
            "artist": "The Dialogue Journal",
            "date_added": "2021-09-13T19:14:53",
            "genre": "Podcast",
            "location": "https://media.blubrry.com/dialogue_journal/www.dialoguejournal.com/wp-content/uploads/podcasts/dialogueoutloud_11.mp3",
            "name": "Dialogue Out Loud #11: Finding Rebecca a Eulogy by Marie Blanchard",
            "persistent_id": "6AA5B1ADD1D43E3B",
            "podcast": true,
            "release_date": "2021-06-22T23:48:32",
            "size": 15405376,
            "sort_album": "Dialogue Journal",
            "sort_artist": "Dialogue Journal",
            "total_time": 770000,
            "track_id": 9732,
            "track_type": "URL",
            "unplayed": true
        },
        {
            "album": "The Dialogue Journal",
            "artist": "The Dialogue Journal",
            "date_added": "2021-09-13T19:14:53",
            "genre": "Podcast",
            "location": "https://media.blubrry.com/dialogue_journal/www.dialoguejournal.com/wp-content/uploads/podcasts/dialoguepodcast_103.mp3",
            "name": "Dialogue Gospel Study #45 with Matthew Bowman",
            "persistent_id": "10CBED88C45670DB",
            "podcast": true,
            "release_date": "2021-06-28T17:38:08",
            "size": 117902226,
            "sort_album": "Dialogue Journal",
            "sort_artist": "Dialogue Journal",
            "total_time": 3684000,
            "track_id": 9734,
            "track_type": "URL",
            "unplayed": true
        },
        {
            "album": "The Dialogue Journal",
            "artist": "The Dialogue Journal",
            "date_added": "2021-09-13T19:14:53",
            "genre": "Podcast",
            "location": "https://media.blubrry.com/dialogue_journal/www.dialoguejournal.com/wp-content/uploads/podcasts/dialoguepodcast_104.mp3",
            "name": "Dialogue Gospel Study #46 with Kimberly Applewhite Teitter",
            "persistent_id": "C707A41ABC70291A",
            "podcast": true,
            "release_date": "2021-07-12T04:16:13",
            "size": 116113361,
            "sort_album": "Dialogue Journal",
            "sort_artist": "Dialogue Journal",
            "total_time": 4838000,
            "track_id": 9736,
            "track_type": "URL",
            "unplayed": true
        },
        {
            "album": "The Dialogue Journal",
            "artist": "The Dialogue Journal",
            "date_added": "2021-09-13T19:14:53",
            "genre": "Podcast",
            "location": "https://media.blubrry.com/dialogue_journal/www.dialoguejournal.com/wp-content/uploads/podcasts/dialoguepodcast_105.mp3",
            "name": "Dialogue Gospel Study #47 w/Joshua Molina",
            "persistent_id": "3E441BDE8CD0E7CF",
            "podcast": true,
            "release_date": "2021-07-25T23:47:48",
            "size": 92323542,
            "sort_album": "Dialogue Journal",
            "sort_artist": "Dialogue Journal",
            "total_time": 3847000,
            "track_id": 9738,
            "track_type": "URL",
            "unplayed": true
        },
        {
            "album": "The Dialogue Journal",
            "artist": "The Dialogue Journal",
            "date_added": "2021-09-13T19:14:53",
            "genre": "Podcast",
            "location": "https://media.blubrry.com/dialogue_journal/www.dialoguejournal.com/wp-content/uploads/podcasts/dialoguebookreport_11.mp3",
            "name": "Dialogue Book Report #11: Mormon Music and Novels",
            "persistent_id": "9E0B41E2D62803CC",
            "podcast": true,
            "release_date": "2021-08-06T00:43:33",
            "size": 120525376,
            "sort_album": "Dialogue Journal",
            "sort_artist": "Dialogue Journal",
            "total_time": 6026000,
            "track_id": 9740,
            "track_type": "URL",
            "unplayed": true
        },
        {
            "album": "The Dialogue Journal",
            "artist": "The Dialogue Journal",
            "date_added": "2021-09-13T19:14:53",
            "genre": "Podcast",
            "location": "https://media.blubrry.com/dialogue_journal/www.dialoguejournal.com/wp-content/uploads/podcasts/dialoguepodcast_106.mp3",
            "name": "Dialogue Gospel Study #48 w/George Handley",
            "persistent_id": "C515AA2BBCD8B0BF",
            "podcast": true,
            "release_date": "2021-08-09T01:34:46",
            "size": 159222770,
            "sort_album": "Dialogue Journal",
            "sort_artist": "Dialogue Journal",
            "total_time": 3980000,
            "track_id": 9742,
            "track_type": "URL",
            "unplayed": true
        },
        {
            "album": "The Dialogue Journal",
            "artist": "The Dialogue Journal",
            "date_added": "2021-09-13T19:14:53",
            "genre": "Podcast",
            "location": "https://media.blubrry.com/dialogue_journal/www.dialoguejournal.com/wp-content/uploads/podcasts/dialoguepodcast_107.mp3",
            "name": "Dialogue Gospel Study #49 w/Page Turner and Heather Harris-Bergevin",
            "persistent_id": "F443A4656521D3A0",
            "podcast": true,
            "release_date": "2021-08-23T00:22:31",
            "size": 111953817,
            "sort_album": "Dialogue Journal",
            "sort_artist": "Dialogue Journal",
            "total_time": 4665000,
            "track_id": 9744,
            "track_type": "URL",
            "unplayed": true
        },
        {
            "album": "The Dialogue Journal",
            "artist": "The Dialogue Journal",
            "bitrate": 160,
            "date_added": "2021-09-13T19:18:09",
            "date_modified": "2021-09-13T19:18:09",
            "genre": "Podcast",
            "kind": "MPEG audio file",
            "location": "https://media.blubrry.com/dialogue_journal/www.dialoguejournal.com/wp-content/uploads/podcasts/dialogueoutloud_12.mp3",
            "name": "Dialogue Out Loud #12: The Lamanite Dilemma: Mormonism and Indigeneity by Monika Brown Crowfoot",
            "normalization": 1230,
            "persistent_id": "75C0EE733092A71E",
            "podcast": true,
            "release_date": "2021-08-23T20:43:34",
            "sample_rate": 48000,
            "size": 21205216,
            "sort_album": "Dialogue Journal",
            "sort_artist": "Dialogue Journal",
            "total_time": 1060000,
            "track_id": 14670,
            "track_type": "URL",
            "unplayed": true,
            "year": 2021
        },
        {
            "album": "The Dialogue Journal",
            "artist": "The Dialogue Journal",
            "bitrate": 160,
            "date_added": "2021-09-13T19:26:55",
            "date_modified": "2021-09-13T19:26:55",
            "genre": "Podcast",
            "kind": "MPEG audio file",
            "location": "https://media.blubrry.com/dialogue_journal/www.dialoguejournal.com/wp-content/uploads/podcasts/dialoguebookreport_12.mp3",
            "name": "Dialogue Book Report #12: Terryl L. Givens on Eugene England",
            "normalization": 1553,
            "persistent_id": "F128DF7B15506998",
            "podcast": true,
            "release_date": "2021-08-31T01:12:41",
            "sample_rate": 44100,
            "size": 50100161,
            "sort_album": "Dialogue Journal",
            "sort_artist": "Dialogue Journal",
            "total_time": 2505000,
            "track_id": 14700,
            "track_type": "URL",
            "unplayed": true,
            "year": 2021
        },
        {
            "album": "The Dialogue Journal",
            "artist": "The Dialogue Journal",
            "bitrate": 160,
            "date_added": "2021-09-13T19:34:06",
            "date_modified": "2021-09-13T19:34:06",
            "genre": "Podcast",
            "kind": "MPEG audio file",
            "location": "https://media.blubrry.com/dialogue_journal/www.dialoguejournal.com/wp-content/uploads/podcasts/dialogueoutloud_13.mp3",
            "name": "Dialogue Out Loud #13: Diné Doctor: A Latter-day Saint Story of Healing by Farina King",
            "normalization": 1230,
            "persistent_id": "B42D4A6CFB3F7A72",
            "podcast": true,
            "release_date": "2021-09-09T22:04:12",
            "sample_rate": 48000,
            "size": 21285376,
            "sort_album": "Dialogue Journal",
            "sort_artist": "Dialogue Journal",
            "total_time": 1064000,
            "track_id": 14724,
            "track_type": "URL",
            "unplayed": true,
            "year": 2021
        },
        {
            "album": "The Dialogue Journal",
            "artist": "The Dialogue Journal",
            "bitrate": 192,
            "date_added": "2021-09-14T19:15:26",
            "date_modified": "2021-09-14T19:15:26",
            "genre": "Podcast",
            "kind": "MPEG audio file",
            "location": "https://media.blubrry.com/dialogue_journal/www.dialoguejournal.com/wp-content/uploads/podcasts/dialoguepodcast_108.mp3",
            "name": "Dialogue Gospel Study #50 w/Charles Beacham",
            "persistent_id": "F96C1B4E1DCC5593",
            "podcast": true,
            "release_date": "2021-09-13T20:15:20",
            "sample_rate": 44100,
            "size": 110454180,
            "sort_album": "Dialogue Journal",
            "sort_artist": "Dialogue Journal",
            "total_time": 4602000,
            "track_id": 14744,
            "track_type": "URL",
            "unplayed": true,
            "year": 2021
        },
        {
            "album": "The Dialogue Journal",
            "artist": "The Dialogue Journal",
            "bitrate": 160,
            "date_added": "2021-09-15T21:13:24",
            "date_modified": "2021-09-15T21:13:24",
            "genre": "Podcast",
            "kind": "MPEG audio file",
            "location": "https://media.blubrry.com/dialogue_journal/www.dialoguejournal.com/wp-content/uploads/podcasts/dialoguebookreport_13.mp3",
            "name": "Dialogue Book Report #13: Kristine Haglund on Eugene England",
            "normalization": 4328,
            "persistent_id": "C7FFE3249B2B58BA",
            "podcast": true,
            "release_date": "2021-09-15T00:30:42",
            "sample_rate": 44100,
            "size": 59605597,
            "sort_album": "Dialogue Journal",
            "sort_artist": "Dialogue Journal",
            "total_time": 2980000,
            "track_id": 14752,
            "track_type": "URL",
            "unplayed": true,
            "year": 2021
        },
        {
            "album": "The Dialogue Journal",
            "artist": "The Dialogue Journal",
            "bitrate": 160,
            "date_added": "2021-09-21T21:04:52",
            "date_modified": "2021-09-21T21:04:52",
            "genre": "Podcast",
            "kind": "MPEG audio file",
            "location": "https://media.blubrry.com/dialogue_journal/www.dialoguejournal.com/wp-content/uploads/podcasts/dialoguepodcasts_topics7.mp3",
            "name": "Dialogue Topic Pages #7: Book of Mormon Topics, Part 1",
            "normalization": 1230,
            "persistent_id": "23B352240B38791C",
            "podcast": true,
            "release_date": "2021-09-21T19:04:27",
            "sample_rate": 44100,
            "size": 51385385,
            "sort_album": "Dialogue Journal",
            "sort_artist": "Dialogue Journal",
            "total_time": 2569000,
            "track_id": 26370,
            "track_type": "URL",
            "unplayed": true,
            "year": 2021
        },
        {
            "album": "The Dialogue Journal",
            "artist": "The Dialogue Journal",
            "bitrate": 192,
            "date_added": "2021-09-27T17:05:04",
            "date_modified": "2021-09-27T17:05:04",
            "genre": "Podcast",
            "kind": "MPEG audio file",
            "location": "https://media.blubrry.com/dialogue_journal/www.dialoguejournal.com/wp-content/uploads/podcasts/dialoguepodcast_109.mp3",
            "name": "Dialogue Gospel Study #51 w/Nathan Oman",
            "persistent_id": "EBCAE2894111AD19",
            "podcast": true,
            "release_date": "2021-09-27T03:15:12",
            "sample_rate": 44100,
            "size": 86685848,
            "sort_album": "Dialogue Journal",
            "sort_artist": "Dialogue Journal",
            "total_time": 3611428,
            "track_id": 26530,
            "track_type": "URL",
            "unplayed": true,
            "year": 2021
        },
        {
            "album": "The Dialogue Journal",
            "artist": "The Dialogue Journal",
            "date_added": "2021-10-12T23:02:11",
            "genre": "Podcast",
            "location": "https://media.blubrry.com/dialogue_journal/www.dialoguejournal.com/wp-content/uploads/podcasts/dialoguepodcast_110.mp3",
            "name": "Dialogue Gospel Study #52 w/Ramona Maile Cutri",
            "persistent_id": "FD7968BAADD6B26C",
            "podcast": true,
            "release_date": "2021-10-12T21:35:25",
            "size": 82196796,
            "sort_album": "Dialogue Journal",
            "sort_artist": "Dialogue Journal",
            "total_time": 3425000,
            "track_id": 26678,
            "track_type": "URL",
            "unplayed": true
        },
        {
            "album": "The Dialogue Journal",
            "artist": "The Dialogue Journal",
            "date_added": "2021-10-21T21:02:21",
            "genre": "Podcast",
            "location": "https://media.blubrry.com/dialogue_journal/www.dialoguejournal.com/wp-content/uploads/podcasts/dialoguepodcast_topics8.mp3",
            "name": "Dialogue Topic Pages #8: Book of Mormon Topics, Part 2",
            "persistent_id": "863A91670B000BCB",
            "podcast": true,
            "release_date": "2021-10-20T16:06:44",
            "size": 44955136,
            "sort_album": "Dialogue Journal",
            "sort_artist": "Dialogue Journal",
            "total_time": 2248000,
            "track_id": 26696,
            "track_type": "URL",
            "unplayed": true
        },
        {
            "album": "The Dialogue Journal",
            "artist": "The Dialogue Journal",
            "date_added": "2021-10-27T20:30:59",
            "genre": "Podcast",
            "location": "https://media.blubrry.com/dialogue_journal/www.dialoguejournal.com/wp-content/uploads/podcasts/dialoguepodcast_111a.mp3",
            "name": "Dialogue Gospel Study #53 w/Jonathan Stapley",
            "persistent_id": "CC9C1FF45AA52128",
            "podcast": true,
            "release_date": "2021-10-25T00:39:20",
            "size": 88012280,
            "sort_album": "Dialogue Journal",
            "sort_artist": "Dialogue Journal",
            "total_time": 3667000,
            "track_id": 26716,
            "track_type": "URL",
            "unplayed": true
        }
    ]
}