{
    "album": "The Very Best Of Dan Fogelberg",
    "songs": [
        {
            "cpil": false,
            "disk": [
                1,
                1
            ],
            "full_path": "D:/iTunes Media/Music/Dan Fogelberg/The Very Best Of Dan Fogelberg/01 Nether Lands.m4a",
            "pgap": false,
            "rel_path": "Dan Fogelberg/The Very Best Of Dan Fogelberg/01 Nether Lands.m4a",
            "tmpo": 0,
            "trkn": [
                1,
                17
            ],
            "©ART": "Dan Fogelberg",
            "©alb": "The Very Best Of Dan Fogelberg",
            "©day": "1977",
            "©gen": "Rock",
            "©nam": "Nether Lands",
            "©too": "iTunes 12.4.3.1",
            "©wrt": "Dan Fogelberg"
        },
        {
            "cpil": false,
            "disk": [
                1,
                1
            ],
            "full_path": "D:/iTunes Media/Music/Dan Fogelberg/The Very Best Of Dan Fogelberg/02 Part Of The Plan.m4a",
            "pgap": false,
            "rel_path": "Dan Fogelberg/The Very Best Of Dan Fogelberg/02 Part Of The Plan.m4a",
            "tmpo": 0,
            "trkn": [
                2,
                17
            ],
            "©ART": "Dan Fogelberg",
            "©alb": "The Very Best Of Dan Fogelberg",
            "©day": "1974",
            "©gen": "Rock",
            "©nam": "Part Of The Plan",
            "©too": "iTunes 12.4.3.1",
            "©wrt": "D.Fogelberg"
        },
        {
            "cpil": false,
            "disk": [
                1,
                1
            ],
            "full_path": "D:/iTunes Media/Music/Dan Fogelberg/The Very Best Of Dan Fogelberg/03 Heart Hotels.m4a",
            "pgap": false,
            "rel_path": "Dan Fogelberg/The Very Best Of Dan Fogelberg/03 Heart Hotels.m4a",
            "tmpo": 0,
            "trkn": [
                3,
                17
            ],
            "©ART": "Dan Fogelberg",
            "©alb": "The Very Best Of Dan Fogelberg",
            "©day": "1979",
            "©gen": "Rock",
            "©nam": "Heart Hotels",
            "©too": "iTunes 12.4.3.1",
            "©wrt": "Dan Fogelberg/Dan Fogelberg"
        },
        {
            "cpil": false,
            "disk": [
                1,
                1
            ],
            "full_path": "D:/iTunes Media/Music/Dan Fogelberg/The Very Best Of Dan Fogelberg/04 Longer.m4a",
            "pgap": false,
            "rel_path": "Dan Fogelberg/The Very Best Of Dan Fogelberg/04 Longer.m4a",
            "tmpo": 0,
            "trkn": [
                4,
                17
            ],
            "©ART": "Dan Fogelberg",
            "©alb": "The Very Best Of Dan Fogelberg",
            "©day": "1979",
            "©gen": "Rock",
            "©nam": "Longer",
            "©too": "iTunes 12.4.3.1",
            "©wrt": "Dan Fogelberg/Dan Fogelberg"
        },
        {
            "cpil": false,
            "disk": [
                1,
                1
            ],
            "full_path": "D:/iTunes Media/Music/Dan Fogelberg/The Very Best Of Dan Fogelberg/05 Hard To Say.m4a",
            "pgap": false,
            "rel_path": "Dan Fogelberg/The Very Best Of Dan Fogelberg/05 Hard To Say.m4a",
            "tmpo": 0,
            "trkn": [
                5,
                17
            ],
            "©ART": "Dan Fogelberg",
            "©alb": "The Very Best Of Dan Fogelberg",
            "©day": "1981",
            "©gen": "Rock",
            "©nam": "Hard To Say",
            "©too": "iTunes 12.4.3.1",
            "©wrt": "Dan Fogelberg"
        },
        {
            "cpil": false,
            "disk": [
                1,
                1
            ],
            "full_path": "D:/iTunes Media/Music/Dan Fogelberg/The Very Best Of Dan Fogelberg/06 Leader Of The Band.m4a",
            "pgap": false,
            "rel_path": "Dan Fogelberg/The Very Best Of Dan Fogelberg/06 Leader Of The Band.m4a",
            "tmpo": 0,
            "trkn": [
                6,
                17
            ],
            "©ART": "Dan Fogelberg",
            "©alb": "The Very Best Of Dan Fogelberg",
            "©day": "1981",
            "©gen": "Rock",
            "©nam": "Leader Of The Band",
            "©too": "iTunes 12.4.3.1",
            "©wrt": "Dan Fogelberg"
        },
        {
            "cpil": false,
            "disk": [
                1,
                1
            ],
            "full_path": "D:/iTunes Media/Music/Dan Fogelberg/The Very Best Of Dan Fogelberg/07 Same Old Lang Syne.m4a",
            "pgap": false,
            "rel_path": "Dan Fogelberg/The Very Best Of Dan Fogelberg/07 Same Old Lang Syne.m4a",
            "tmpo": 0,
            "trkn": [
                7,
                17
            ],
            "©ART": "Dan Fogelberg",
            "©alb": "The Very Best Of Dan Fogelberg",
            "©day": "1980",
            "©gen": "Rock",
            "©nam": "Same Old Lang Syne",
            "©too": "iTunes 12.4.3.1",
            "©wrt": "Dan Fogelberg"
        },
        {
            "cpil": false,
            "disk": [
                1,
                1
            ],
            "full_path": "D:/iTunes Media/Music/Dan Fogelberg/The Very Best Of Dan Fogelberg/08 Run For The Roses.m4a",
            "pgap": false,
            "rel_path": "Dan Fogelberg/The Very Best Of Dan Fogelberg/08 Run For The Roses.m4a",
            "tmpo": 0,
            "trkn": [
                8,
                17
            ],
            "©ART": "Dan Fogelberg",
            "©alb": "The Very Best Of Dan Fogelberg",
            "©day": "1981",
            "©gen": "Rock",
            "©nam": "Run For The Roses",
            "©too": "iTunes 12.4.3.1",
            "©wrt": "Dan Fogelberg/John Philip Sousa"
        },
        {
            "cpil": false,
            "disk": [
                1,
                1
            ],
            "full_path": "D:/iTunes Media/Music/Dan Fogelberg/The Very Best Of Dan Fogelberg/09 Make Love Stay.m4a",
            "pgap": false,
            "rel_path": "Dan Fogelberg/The Very Best Of Dan Fogelberg/09 Make Love Stay.m4a",
            "tmpo": 0,
            "trkn": [
                9,
                17
            ],
            "©ART": "Dan Fogelberg",
            "©alb": "The Very Best Of Dan Fogelberg",
            "©day": "1982",
            "©gen": "Rock",
            "©nam": "Make Love Stay",
            "©too": "iTunes 12.4.3.1",
            "©wrt": "Dan Fogelberg"
        },
        {
            "cpil": false,
            "disk": [
                1,
                1
            ],
            "full_path": "D:/iTunes Media/Music/Dan Fogelberg/The Very Best Of Dan Fogelberg/10 Missing You.m4a",
            "pgap": false,
            "rel_path": "Dan Fogelberg/The Very Best Of Dan Fogelberg/10 Missing You.m4a",
            "tmpo": 0,
            "trkn": [
                10,
                17
            ],
            "©ART": "Dan Fogelberg",
            "©alb": "The Very Best Of Dan Fogelberg",
            "©day": "1982",
            "©gen": "Rock",
            "©nam": "Missing You",
            "©too": "iTunes 12.4.3.1",
            "©wrt": "Dan Fogelberg"
        },
        {
            "cpil": false,
            "disk": [
                1,
                1
            ],
            "full_path": "D:/iTunes Media/Music/Dan Fogelberg/The Very Best Of Dan Fogelberg/11 The Language Of Love.m4a",
            "pgap": false,
            "rel_path": "Dan Fogelberg/The Very Best Of Dan Fogelberg/11 The Language Of Love.m4a",
            "tmpo": 0,
            "trkn": [
                11,
                17
            ],
            "©ART": "Dan Fogelberg",
            "©alb": "The Very Best Of Dan Fogelberg",
            "©day": "1984",
            "©gen": "Rock",
            "©nam": "The Language Of Love",
            "©too": "iTunes 12.4.3.1",
            "©wrt": "Dan Fogelberg"
        },
        {
            "cpil": false,
            "disk": [
                1,
                1
            ],
            "full_path": "D:/iTunes Media/Music/Dan Fogelberg/The Very Best Of Dan Fogelberg/12 Believe In Me.m4a",
            "pgap": false,
            "rel_path": "Dan Fogelberg/The Very Best Of Dan Fogelberg/12 Believe In Me.m4a",
            "tmpo": 0,
            "trkn": [
                12,
                17
            ],
            "©ART": "Dan Fogelberg",
            "©alb": "The Very Best Of Dan Fogelberg",
            "©day": "1984",
            "©gen": "Rock",
            "©nam": "Believe In Me",
            "©too": "iTunes 12.4.3.1",
            "©wrt": "Dan Fogelberg"
        },
        {
            "cpil": false,
            "disk": [
                1,
                1
            ],
            "full_path": "D:/iTunes Media/Music/Dan Fogelberg/The Very Best Of Dan Fogelberg/13 Lonely In Love.m4a",
            "pgap": false,
            "rel_path": "Dan Fogelberg/The Very Best Of Dan Fogelberg/13 Lonely In Love.m4a",
            "tmpo": 0,
            "trkn": [
                13,
                17
            ],
            "©ART": "Dan Fogelberg",
            "©alb": "The Very Best Of Dan Fogelberg",
            "©day": "1987",
            "©gen": "Rock",
            "©nam": "Lonely In Love",
            "©too": "iTunes 12.4.3.1",
            "©wrt": "Dan Fogelberg"
        },
        {
            "cpil": false,
            "disk": [
                1,
                1
            ],
            "full_path": "D:/iTunes Media/Music/Dan Fogelberg/The Very Best Of Dan Fogelberg/14 She Don't Look Back.m4a",
            "pgap": false,
            "rel_path": "Dan Fogelberg/The Very Best Of Dan Fogelberg/14 She Don't Look Back.m4a",
            "tmpo": 0,
            "trkn": [
                14,
                17
            ],
            "©ART": "Dan Fogelberg",
            "©alb": "The Very Best Of Dan Fogelberg",
            "©day": "1987",
            "©gen": "Rock",
            "©nam": "She Don't Look Back",
            "©too": "iTunes 12.4.3.1",
            "©wrt": "Dan Fogelberg"
        },
        {
            "cpil": false,
            "disk": [
                1,
                1
            ],
            "full_path": "D:/iTunes Media/Music/Dan Fogelberg/The Very Best Of Dan Fogelberg/15 Rhythm Of The Rain.m4a",
            "pgap": false,
            "rel_path": "Dan Fogelberg/The Very Best Of Dan Fogelberg/15 Rhythm Of The Rain.m4a",
            "tmpo": 0,
            "trkn": [
                15,
                17
            ],
            "©ART": "Dan Fogelberg",
            "©alb": "The Very Best Of Dan Fogelberg",
            "©day": "1990",
            "©gen": "Rock",
            "©nam": "Rhythm Of The Rain",
            "©too": "iTunes 12.4.3.1",
            "©wrt": "John Gummoe"
        },
        {
            "cpil": false,
            "disk": [
                1,
                1
            ],
            "full_path": "D:/iTunes Media/Music/Dan Fogelberg/The Very Best Of Dan Fogelberg/16 Magic Every Moment.m4a",
            "pgap": false,
            "rel_path": "Dan Fogelberg/The Very Best Of Dan Fogelberg/16 Magic Every Moment.m4a",
            "tmpo": 0,
            "trkn": [
                16,
                17
            ],
            "©ART": "Dan Fogelberg",
            "©alb": "The Very Best Of Dan Fogelberg",
            "©day": "1993",
            "©gen": "Rock",
            "©nam": "Magic Every Moment",
            "©too": "iTunes 12.4.3.1",
            "©wrt": "Dan Fogelberg"
        },
        {
            "cpil": false,
            "disk": [
                1,
                1
            ],
            "full_path": "D:/iTunes Media/Music/Dan Fogelberg/The Very Best Of Dan Fogelberg/17 A Love Like This.m4a",
            "pgap": false,
            "rel_path": "Dan Fogelberg/The Very Best Of Dan Fogelberg/17 A Love Like This.m4a",
            "tmpo": 0,
            "trkn": [
                17,
                17
            ],
            "©ART": "Dan Fogelberg",
            "©alb": "The Very Best Of Dan Fogelberg",
            "©day": "1993",
            "©gen": "Rock",
            "©nam": "A Love Like This",
            "©too": "iTunes 12.4.3.1",
            "©wrt": "Dan Fogelberg"
        }
    ]
}