{
    "album": "BYU Lectures",
    "songs": [
        {
            "album": "BYU Lectures",
            "artist": "Hugh W. Nibley",
            "copyright": "© 1964 Brigham Young University --All rights reserved",
            "date": "1964",
            "discnumber": "1/1",
            "full_path": "C:/Users/bruce/Music/iTunes/iTunes Media/Music/Hugh W. Nibley/BYU Lectures/01 Earliest Christians According to.mp3",
            "genre": "Talk: Religious",
            "rel_path": "Hugh W. Nibley/BYU Lectures/01 Earliest Christians According to.mp3",
            "title": "Earliest Christians According to Newly Discovery Papyri",
            "tracknumber": "1/1"
        },
        {
            "album": "BYU Lectures",
            "artist": "Hugh W. Nibley",
            "copyright": "© 1963 Brigham Young University --All rights reserved.",
            "date": "1963",
            "discnumber": "1/1",
            "full_path": "C:/Users/bruce/Music/iTunes/iTunes Media/Music/Hugh W. Nibley/BYU Lectures/01 Jerusalem's Formula for Peace.mp3",
            "genre": "Talk: Religious",
            "rel_path": "Hugh W. Nibley/BYU Lectures/01 Jerusalem's Formula for Peace.mp3",
            "title": "Jerusalem's Formula for Peace",
            "tracknumber": "1/1"
        },
        {
            "album": "BYU Lectures",
            "artist": "Hugh W. Nibley",
            "date": "1956",
            "discnumber": "1/1",
            "full_path": "C:/Users/bruce/Music/iTunes/iTunes Media/Music/Hugh W. Nibley/BYU Lectures/01 Lessons of the Sixth Century.mp3",
            "genre": "Talk: Religious",
            "rel_path": "Hugh W. Nibley/BYU Lectures/01 Lessons of the Sixth Century.mp3",
            "title": "Lessons of the Sixth Century",
            "tracknumber": "1/1"
        },
        {
            "album": "BYU Lectures",
            "artist": "Hugh W. Nibley",
            "copyright": "© 1976 Brigham Young University --All rights reserved.",
            "date": "1976",
            "discnumber": "1/1",
            "full_path": "C:/Users/bruce/Music/iTunes/iTunes Media/Music/Hugh W. Nibley/BYU Lectures/01 More Brigham Young on Education.mp3",
            "genre": "Talk: Religious",
            "rel_path": "Hugh W. Nibley/BYU Lectures/01 More Brigham Young on Education.mp3",
            "title": "More Brigham Young on Education",
            "tracknumber": "1/1"
        },
        {
            "album": "BYU Lectures",
            "artist": "Hugh W. Nibley",
            "copyright": "© 1965 Brigham Young University --All rights reserved.",
            "date": "1965",
            "discnumber": "1/1",
            "full_path": "C:/Users/bruce/Music/iTunes/iTunes Media/Music/Hugh W. Nibley/BYU Lectures/01 New Light on Israel and Her Neigh.mp3",
            "genre": "Talk: Religious",
            "rel_path": "Hugh W. Nibley/BYU Lectures/01 New Light on Israel and Her Neigh.mp3",
            "title": "New Light on Israel and Her Neighbors (Part I)",
            "tracknumber": "1/1"
        },
        {
            "album": "BYU Lectures",
            "artist": "Hugh W. Nibley",
            "copyright": "© 1965 Brigham Young University --All rights reserved.",
            "date": "1965",
            "discnumber": "1/1",
            "full_path": "C:/Users/bruce/Music/iTunes/iTunes Media/Music/Hugh W. Nibley/BYU Lectures/01 Rediscovery of the Apocrypha (Par.mp3",
            "genre": "Talk: Religious",
            "rel_path": "Hugh W. Nibley/BYU Lectures/01 Rediscovery of the Apocrypha (Par.mp3",
            "title": "Rediscovery of the Apocrypha (Part 2)",
            "tracknumber": "1/1"
        }
    ]
}